overlaymodule/__init__.py
overlaymodule/finders.py
overlaymodule/loaders.py
overlaymodule-0.0.3.dist-info/METADATA
overlaymodule-0.0.3.dist-info/WHEEL
overlaymodule-0.0.3.dist-info/top_level.txt
overlaymodule-0.0.3.dist-info/RECORD
