Metadata-Version: 2.1
Name: overlaymodule
Version: 0.0.3
Summary: A Special Module Loader that can load modules with overlays.
Home-page: https://github.com/llacroix/overlaymodule
Author: Loïc Faure-Lacroix
Author-email: lamerstar@gmail.com
Project-URL: Bug Tracker, https://github.com/llacroix/overlaymodule/issues
Classifier: Programming Language :: Python :: 3
Classifier: License :: OSI Approved :: MIT License
Classifier: Operating System :: OS Independent
Requires-Python: >=3.4
